higlass/__init__.py
higlass/_scale.py
higlass/_tileset_registry.py
higlass/_utils.py
higlass/_widget.py
higlass/api.py
higlass/server.py
higlass/tilesets.py
higlass/types.ts
higlass/widget.js
higlass_python-1.3.3.dist-info/METADATA
higlass_python-1.3.3.dist-info/WHEEL
higlass_python-1.3.3.dist-info/licenses/LICENSE
higlass_python-1.3.3.dist-info/RECORD
