Metadata-Version: 2.4
Name: higlass-python
Version: 1.3.3
Summary: Python bindings for HiGlass
Project-URL: homepage, https://github.com/higlass/higlass-python
Author-email: Fritz Lekschas <code@lekschas.de>, Nezar Abdennur <nabdennur@gmail.com>, Peter Kerpdjiev <pkerpedjiev@gmail.com>, Trevor Manz <trevor.j.manz@gmail.com>
License: MIT
License-File: LICENSE
Classifier: Development Status :: 3 - Alpha
Classifier: Intended Audience :: Developers
Classifier: Operating System :: OS Independent
Classifier: Programming Language :: Python
Classifier: Programming Language :: Python :: 3
Classifier: Programming Language :: Python :: 3.8
Classifier: Programming Language :: Python :: 3.9
Classifier: Programming Language :: Python :: 3.10
Classifier: Programming Language :: Python :: 3.11
Requires-Python: >=3.8
Requires-Dist: anywidget>=0.9.0
Requires-Dist: higlass-schema>=0.2.0
Requires-Dist: typing-extensions; python_version < '3.9'
